madys/__init__.py
madys/madys.py
madys/utils/filters.pkl
madys/utils/models.pkl
madys-1.3.0.dist-info/LICENSE
madys-1.3.0.dist-info/METADATA
madys-1.3.0.dist-info/WHEEL
madys-1.3.0.dist-info/top_level.txt
madys-1.3.0.dist-info/RECORD
