Metadata-Version: 2.1
Name: madys
Version: 1.3.0
Summary: Manifold Age Determination for Young Stars
Home-page: https://github.com/vsquicciarini/madys
Author: Vito Squicciarini
Author-email: vito.squicciarini@inaf.it
Project-URL: Bug Tracker, https://github.com/vsquicciarini/madys/issues
Classifier: Programming Language :: Python :: 3
Classifier: License :: OSI Approved :: MIT License
Classifier: Operating System :: OS Independent
Requires-Python: >=3.6
License-File: LICENSE
Requires-Dist: numpy
Requires-Dist: scipy
Requires-Dist: astropy
Requires-Dist: pandas
Requires-Dist: matplotlib
Requires-Dist: astroquery
Requires-Dist: h5py
Requires-Dist: lxml
